{
  "id": "1148453",
  "url": "https://www.supercarros.com/mitsubishi-fuso/1148453/",
  "title": "Mitsubishi Fuso Canter",
  "year": 2025,
  "fuel": "Diesel",
  "condition": "Nuevo",
  "price_currency": "USD",
  "price_amount": 46000.0,
  "thumbnail": "https://img.supercarros.com/AdsPhotos/282x188/5/9402017.jpg",
  "photo_ids": [
    "9402017",
    "9402018",
    "9402019",
    "9402020",
    "9402021",
    "9402022",
    "9402023"
  ],
  "badges": [
    "promo-ANADIVE"
  ],
  "scraped_at": "2025-10-05T19:23:32Z",
  "source": "https://www.supercarros.com/v.pesados/"
}