{
  "id": "1247973",
  "url": "https://www.supercarros.com/hyundai-h100/1247973/",
  "title": "Hyundai H-100 Camion",
  "year": 2025,
  "fuel": "Diesel",
  "condition": "Nuevo",
  "price_currency": "USD",
  "price_amount": 24995.0,
  "thumbnail": "https://img.supercarros.com/AdsPhotos/282x188/5/13713761.jpg",
  "photo_ids": [
    "10526739",
    "10526741",
    "10526742",
    "13713761",
    "13713762",
    "13713763",
    "13713764",
    "13713765",
    "13713766",
    "13713767",
    "13713768",
    "13713769"
  ],
  "badges": [],
  "scraped_at": "2025-10-05T19:22:47Z",
  "source": "https://www.supercarros.com/v.pesados/"
}