{
  "id": "1276449",
  "url": "https://www.supercarros.com/isuzu-reward/1276449/",
  "title": "Isuzu REWARD",
  "year": 2026,
  "fuel": "Diesel",
  "condition": "Nuevo",
  "price_currency": "USD",
  "price_amount": 48200.0,
  "thumbnail": "https://img.supercarros.com/AdsPhotos/282x188/5/13495921.jpg",
  "photo_ids": [
    "13495910",
    "13495912",
    "13495914",
    "13495916",
    "13495918",
    "13495919",
    "13495920",
    "13495921"
  ],
  "badges": [
    "promo-ANADIVE"
  ],
  "scraped_at": "2025-10-05T19:23:59Z",
  "source": "https://www.supercarros.com/v.pesados/"
}