{
  "id": "1386351",
  "url": "https://www.supercarros.com/jac-hfc/1386351/",
  "title": "Jac HFC 1063K",
  "year": 2023,
  "fuel": "Diesel",
  "condition": "Nuevo",
  "price_currency": "USD",
  "price_amount": 51990.0,
  "thumbnail": "https://img.supercarros.com/AdsPhotos/282x188/5/12024011.jpg",
  "photo_ids": [
    "12024011",
    "12024012",
    "12024013",
    "12024014",
    "12024015",
    "12024016",
    "12024020",
    "12024019",
    "12024021",
    "12024017",
    "12024018",
    "12024022"
  ],
  "badges": [
    "promo-ANADIVE"
  ],
  "scraped_at": "2025-10-05T19:23:30Z",
  "source": "https://www.supercarros.com/v.pesados/"
}