{
  "id": "1406476",
  "url": "https://www.supercarros.com/isuzu-nqr/1406476/",
  "title": "Isuzu NQR",
  "year": 2005,
  "fuel": "Diesel",
  "condition": "Usado",
  "price_currency": "DOP",
  "price_amount": 670000.0,
  "thumbnail": "https://img.supercarros.com/AdsPhotos/282x188/5/12242953.jpg",
  "photo_ids": [
    "12242951",
    "12242952",
    "12242953",
    "12242954",
    "12242955",
    "12242956",
    "12242957",
    "12242958",
    "12242959"
  ],
  "badges": [
    "promo-ADECI"
  ],
  "scraped_at": "2025-10-05T19:21:37Z",
  "source": "https://www.supercarros.com/buscar?OrderColumn=Id&OrderDirection=DESC&PagingItemsPerPage=24"
}