{
  "id": "1424374",
  "url": "https://www.supercarros.com/forland-f200/1424374/",
  "title": "Forland F200 S Furgon",
  "year": 2026,
  "fuel": "Diesel",
  "condition": "Nuevo",
  "price_currency": "USD",
  "price_amount": 20990.0,
  "thumbnail": "https://img.supercarros.com/AdsPhotos/282x188/5/12443390.jpg",
  "photo_ids": [
    "12443386",
    "12443387",
    "12443388",
    "12443389",
    "12443390",
    "12443391",
    "12443392",
    "12443393",
    "12443394",
    "12443395",
    "12443396"
  ],
  "badges": [
    "promo-ANADIVE"
  ],
  "scraped_at": "2025-10-05T19:23:44Z",
  "source": "https://www.supercarros.com/v.pesados/"
}