{
  "id": "1440489",
  "url": "https://www.supercarros.com/bmw-f850/1440489/",
  "title": "BMW F-850 40 Aniversario",
  "year": 2022,
  "fuel": "Gasolina",
  "condition": "Usado",
  "price_currency": "USD",
  "price_amount": 21900.0,
  "thumbnail": "https://img.supercarros.com/AdsPhotos/282x188/5/12621634.jpg",
  "photo_ids": [
    "12621624",
    "12621625",
    "12621626",
    "12621627",
    "12621628",
    "12621629",
    "12621630",
    "12621631",
    "12621632",
    "12621633",
    "12621634",
    "12621635"
  ],
  "badges": [],
  "scraped_at": "2025-10-05T19:24:08Z",
  "source": "https://www.supercarros.com/motores/"
}