{
  "id": "1465216",
  "url": "https://www.supercarros.com/toyota-aqua/1465216/",
  "title": "Toyota Aqua",
  "year": 2018,
  "fuel": "Gasolina",
  "condition": "Usado",
  "price_currency": "DOP",
  "price_amount": 655000.0,
  "thumbnail": "https://img.supercarros.com/AdsPhotos/282x188/5/12896487.jpg",
  "photo_ids": [
    "12896487",
    "12896488",
    "12896489",
    "12896491",
    "12896492",
    "12896490",
    "12896493",
    "12896494",
    "12896495",
    "12896496",
    "12896497",
    "12896498"
  ],
  "badges": [],
  "scraped_at": "2025-10-05T19:22:28Z",
  "source": "https://www.supercarros.com/buscar?OrderColumn=Id&OrderDirection=DESC&PagingItemsPerPage=24"
}