{
  "id": "1492500",
  "url": "https://www.supercarros.com/audi-a4/1492500/",
  "title": "Audi A4 Turbo S-Line",
  "year": 2019,
  "fuel": "Gasolina",
  "condition": "Usado",
  "price_currency": "USD",
  "price_amount": 24900.0,
  "thumbnail": "https://img.supercarros.com/AdsPhotos/282x188/5/13198948.jpg",
  "photo_ids": [
    "13198948",
    "13198949",
    "13198950",
    "13198951",
    "13198952",
    "13198953",
    "13198954",
    "13198955",
    "13198959"
  ],
  "badges": [
    "promo-ANADIVE"
  ],
  "scraped_at": "2025-10-05T19:22:19Z",
  "source": "https://www.supercarros.com/buscar?OrderColumn=Id&OrderDirection=DESC&PagingItemsPerPage=24"
}