{
  "id": "1512991",
  "url": "https://www.supercarros.com/mercedesbenz-clase gle/1512991/",
  "title": "Mercedes-Benz Clase GLE 350 4Matic AMG",
  "year": 2020,
  "fuel": "Gasolina",
  "condition": "Usado",
  "price_currency": "USD",
  "price_amount": 58500.0,
  "thumbnail": "https://img.supercarros.com/AdsPhotos/282x188/5/13427576.jpg",
  "photo_ids": [
    "13427576",
    "13427577",
    "13427578",
    "13427579",
    "13427580",
    "13427581",
    "13427582",
    "13427583",
    "13427584",
    "13427585"
  ],
  "badges": [],
  "scraped_at": "2025-10-05T19:22:24Z",
  "source": "https://www.supercarros.com/buscar?OrderColumn=Id&OrderDirection=DESC&PagingItemsPerPage=24"
}