{
  "id": "1519077",
  "url": "https://www.supercarros.com/isuzu-npr/1519077/",
  "title": "Isuzu NPR 16 pies",
  "year": 2026,
  "fuel": "Gasolina",
  "condition": "Nuevo",
  "price_currency": "USD",
  "price_amount": 46200.0,
  "thumbnail": "https://img.supercarros.com/AdsPhotos/282x188/5/13496513.jpg",
  "photo_ids": [
    "13496513",
    "13496514",
    "13496515",
    "13496516",
    "13496517",
    "13496518",
    "13496519",
    "13496520"
  ],
  "badges": [],
  "scraped_at": "2025-10-05T19:23:00Z",
  "source": "https://www.supercarros.com/v.pesados/"
}