{
  "id": "1522854",
  "url": "https://www.supercarros.com/ducati-monster/1522854/",
  "title": "Ducati Monster 821",
  "year": 2019,
  "fuel": "Gasolina",
  "condition": "Usado",
  "price_currency": "USD",
  "price_amount": 15990.0,
  "thumbnail": "https://img.supercarros.com/AdsPhotos/282x188/5/13538342.jpg",
  "photo_ids": [
    "13538337",
    "13538338",
    "13538339",
    "13538340",
    "13538341",
    "13538342",
    "13538343",
    "13538344",
    "13538345",
    "13538346",
    "13538347"
  ],
  "badges": [],
  "scraped_at": "2025-10-05T20:39:14Z",
  "source": "https://www.supercarros.com/motores/"
}