{
  "id": "1522053",
  "url": "https://www.supercarros.com/nissan-sentra/1522053/",
  "title": "Nissan Sentra",
  "year": 2020,
  "fuel": "Gasolina",
  "condition": "Usado",
  "price_currency": "DOP",
  "price_amount": 850000.0,
  "thumbnail": "https://img.supercarros.com/AdsPhotos/282x188/5/13529499.jpg",
  "photo_ids": [
    "13529499",
    "13529500",
    "13529501",
    "13529502",
    "13529503",
    "13529504",
    "13529505",
    "13529506",
    "13529507",
    "13529508",
    "13529509"
  ],
  "badges": [],
  "scraped_at": "2025-10-05T19:21:49Z",
  "source": "https://www.supercarros.com/buscar?OrderColumn=Id&OrderDirection=DESC&PagingItemsPerPage=24"
}