{
  "id": "1529020",
  "url": "https://www.supercarros.com/nissan-kicks/1529020/",
  "title": "Nissan Kicks",
  "year": 2022,
  "fuel": "Gasolina",
  "condition": "Usado",
  "price_currency": "DOP",
  "price_amount": 1050000.0,
  "thumbnail": "https://img.supercarros.com/AdsPhotos/282x188/5/13608610.jpg",
  "photo_ids": [
    "13608610",
    "13608612",
    "13608613",
    "13608615",
    "13608616",
    "13608617",
    "13608619",
    "13608621",
    "13608622",
    "13608624",
    "13608625",
    "13608627"
  ],
  "badges": [],
  "scraped_at": "2025-10-05T20:38:58Z",
  "source": "https://www.supercarros.com/buscar?OrderColumn=Id&OrderDirection=DESC&PagingItemsPerPage=24"
}