{
  "id": "1530000",
  "url": "https://www.supercarros.com/honda-navi/1530000/",
  "title": "Honda Navi",
  "year": 2025,
  "fuel": "Gasolina",
  "condition": "Nuevo",
  "price_currency": "USD",
  "price_amount": 1895.0,
  "thumbnail": "https://img.supercarros.com/AdsPhotos/282x188/5/13619753.jpg",
  "photo_ids": [
    "13619753",
    "13619754",
    "13619756",
    "13619757",
    "13619758",
    "13619760",
    "13619761",
    "13619763"
  ],
  "badges": [
    "promo-ANADIVE"
  ],
  "scraped_at": "2025-10-05T19:24:16Z",
  "source": "https://www.supercarros.com/motores/"
}