{
  "id": "1537988",
  "url": "https://www.supercarros.com/toyota-landcruiserprado/1537988/",
  "title": "Toyota Land Cruiser Prado",
  "year": 2013,
  "fuel": "Diesel",
  "condition": "Usado",
  "price_currency": "USD",
  "price_amount": 35900.0,
  "thumbnail": "https://img.supercarros.com/AdsPhotos/282x188/5/13700296.jpg",
  "photo_ids": [
    "13700296",
    "13700297",
    "13700298",
    "13700299",
    "13700300",
    "13700301",
    "13700302",
    "13700303",
    "13700304"
  ],
  "badges": [],
  "scraped_at": "2025-10-05T20:38:50Z",
  "source": "https://www.supercarros.com/buscar?OrderColumn=Id&OrderDirection=DESC&PagingItemsPerPage=24"
}