{
  "id": "1539554",
  "url": "https://www.supercarros.com/canam-maverick/1539554/",
  "title": "Can-Am Maverick MAX XRS SMART SHOX",
  "year": 2022,
  "fuel": "Gasolina",
  "condition": "Usado",
  "price_currency": "USD",
  "price_amount": 46000.0,
  "thumbnail": "https://img.supercarros.com/AdsPhotos/282x188/5/13717819.jpg",
  "photo_ids": [
    "13717819",
    "13717820",
    "13717821",
    "13717822",
    "13717823",
    "13717824",
    "13717825",
    "13717826"
  ],
  "badges": [
    "promo-ADECI"
  ],
  "scraped_at": "2025-10-05T20:39:16Z",
  "source": "https://www.supercarros.com/motores/"
}