{
  "id": "1542967",
  "url": "https://www.supercarros.com/hyundai-h100/1542967/",
  "title": "Hyundai H-100",
  "year": 2023,
  "fuel": "Diesel",
  "condition": "Usado",
  "price_currency": "USD",
  "price_amount": 17900.0,
  "thumbnail": "https://img.supercarros.com/AdsPhotos/282x188/5/13755528.jpg",
  "photo_ids": [
    "13755521",
    "13755522",
    "13755523",
    "13755524",
    "13755525",
    "13755526",
    "13755527",
    "13755528",
    "13755529",
    "13755530"
  ],
  "badges": [],
  "scraped_at": "2025-10-05T19:23:40Z",
  "source": "https://www.supercarros.com/v.pesados/"
}