{
  "id": "1543475",
  "url": "https://www.supercarros.com/ktm-sxf/1543475/",
  "title": "KTM SX-F",
  "year": 2025,
  "fuel": "Gasolina",
  "condition": "Nuevo",
  "price_currency": "USD",
  "price_amount": 15300.0,
  "thumbnail": "https://img.supercarros.com/AdsPhotos/282x188/5/13761266.jpg",
  "photo_ids": [
    "13761266",
    "13761267",
    "13761268",
    "13761269",
    "13761270",
    "13761271",
    "13761272",
    "13761273",
    "13761274",
    "13761275",
    "13761276",
    "13761277"
  ],
  "badges": [
    "promo-ANADIVE"
  ],
  "scraped_at": "2025-10-05T20:39:16Z",
  "source": "https://www.supercarros.com/motores/"
}