{
  "id": "1548517",
  "url": "https://www.supercarros.com/chevrolet-colorado/1548517/",
  "title": "Chevrolet Colorado LT",
  "year": 2020,
  "fuel": "Gasolina",
  "condition": "Usado",
  "price_currency": "DOP",
  "price_amount": 1595000.0,
  "thumbnail": "https://img.supercarros.com/AdsPhotos/282x188/5/13818345.jpg",
  "photo_ids": [
    "13818345",
    "13818346",
    "13818347",
    "13818348",
    "13818349",
    "13818350",
    "13818351"
  ],
  "badges": [],
  "scraped_at": "2025-10-05T19:21:43Z",
  "source": "https://www.supercarros.com/buscar?OrderColumn=Id&OrderDirection=DESC&PagingItemsPerPage=24"
}