{
  "id": "1550690",
  "url": "https://www.supercarros.com/hino-338/1550690/",
  "title": "Hino 338",
  "year": 2017,
  "fuel": "Diesel",
  "condition": "Usado",
  "price_currency": "USD",
  "price_amount": 38900.0,
  "thumbnail": "https://img.supercarros.com/AdsPhotos/282x188/5/13859399.jpg",
  "photo_ids": [
    "13859399",
    "13882213",
    "13882214",
    "13882215",
    "13882216",
    "13882217",
    "13882218",
    "13882219",
    "13882220",
    "13882221",
    "13882222",
    "13882223"
  ],
  "badges": [
    "promo-ADECI"
  ],
  "scraped_at": "2025-10-05T19:22:45Z",
  "source": "https://www.supercarros.com/v.pesados/"
}