{
  "id": "1550267",
  "url": "https://www.supercarros.com/chevrolet-cruze/1550267/",
  "title": "Chevrolet Cruze LS",
  "year": 2017,
  "fuel": "Gasolina",
  "condition": "Usado",
  "price_currency": "DOP",
  "price_amount": 555000.0,
  "thumbnail": "https://img.supercarros.com/AdsPhotos/282x188/5/13837530.jpg",
  "photo_ids": [
    "13837530",
    "13837531",
    "13837533",
    "13837534",
    "13837535",
    "13837536",
    "13837537",
    "13837538",
    "13837539",
    "13837540",
    "13837541"
  ],
  "badges": [],
  "scraped_at": "2025-10-05T20:38:56Z",
  "source": "https://www.supercarros.com/buscar?OrderColumn=Id&OrderDirection=DESC&PagingItemsPerPage=24"
}