{
  "id": "1552104",
  "url": "https://www.supercarros.com/kia-bongo/1552104/",
  "title": "Kia Bongo III",
  "year": 2020,
  "fuel": "Diesel",
  "condition": "Usado",
  "price_currency": "DOP",
  "price_amount": 1100000.0,
  "thumbnail": "https://img.supercarros.com/AdsPhotos/282x188/5/13858228.jpg",
  "photo_ids": [
    "13858228",
    "13858229",
    "13858230",
    "13858231",
    "13858232",
    "13858233",
    "13858234",
    "13858235"
  ],
  "badges": [],
  "scraped_at": "2025-10-05T19:23:51Z",
  "source": "https://www.supercarros.com/v.pesados/"
}