{
  "id": "1552252",
  "url": "https://www.supercarros.com/canam-maverick/1552252/",
  "title": "Can-Am Maverick R MAX X RS SMART SHOX",
  "year": 2025,
  "fuel": "Gasolina",
  "condition": "Nuevo",
  "price_currency": "USD",
  "price_amount": 74900.0,
  "thumbnail": "https://img.supercarros.com/AdsPhotos/282x188/5/13859866.jpg",
  "photo_ids": [
    "13859866",
    "13859867",
    "13859868",
    "13859869",
    "13859870"
  ],
  "badges": [],
  "scraped_at": "2025-10-05T19:24:08Z",
  "source": "https://www.supercarros.com/motores/"
}