{
  "id": "1553079",
  "url": "https://www.supercarros.com/newholland-tl95e/1553079/",
  "title": "New Holland TL95E",
  "year": 2018,
  "fuel": "Diesel",
  "condition": "Usado",
  "price_currency": "DOP",
  "price_amount": 1175000.0,
  "thumbnail": "https://img.supercarros.com/AdsPhotos/282x188/5/13869048.jpg",
  "photo_ids": [
    "13869048",
    "13869049",
    "13869050",
    "13869051",
    "13869052"
  ],
  "badges": [
    "promo-ANADIVE"
  ],
  "scraped_at": "2025-10-05T19:23:15Z",
  "source": "https://www.supercarros.com/v.pesados/"
}